{
  "id": "1652563",
  "name": "association",
  "font_family": "iconfont",
  "css_prefix_text": "icon",
  "description": "",
  "glyphs": [
    {
      "icon_id": "14401646",
      "name": "checkmark",
      "font_class": "checkmark",
      "unicode": "e65b",
      "unicode_decimal": 58971
    },
    {
      "icon_id": "7766710",
      "name": "icon_addmessage",
      "font_class": "icon_addmessage",
      "unicode": "eb90",
      "unicode_decimal": 60304
    },
    {
      "icon_id": "7766713",
      "name": "icon_addperson",
      "font_class": "icon_addperson",
      "unicode": "eb91",
      "unicode_decimal": 60305
    },
    {
      "icon_id": "7766731",
      "name": "icon_delete",
      "font_class": "icon_delete",
      "unicode": "eb93",
      "unicode_decimal": 60307
    },
    {
      "icon_id": "7766753",
      "name": "icon_likegood",
      "font_class": "icon_likegood",
      "unicode": "eb97",
      "unicode_decimal": 60311
    },
    {
      "icon_id": "7766791",
      "name": "icon_share",
      "font_class": "icon_share",
      "unicode": "eb9e",
      "unicode_decimal": 60318
    },
    {
      "icon_id": "7766810",
      "name": "icon_workmore",
      "font_class": "icon_workmore",
      "unicode": "eba1",
      "unicode_decimal": 60321
    },
    {
      "icon_id": "7772200",
      "name": "icon_likegood_fill",
      "font_class": "icon_likegood_fill",
      "unicode": "ebaa",
      "unicode_decimal": 60330
    },
    {
      "icon_id": "7772233",
      "name": "icon_setting_fill",
      "font_class": "icon_setting_fill",
      "unicode": "ebaf",
      "unicode_decimal": 60335
    },
    {
      "icon_id": "11474220",
      "name": "bussiness-man",
      "font_class": "bussiness-man",
      "unicode": "e6ef",
      "unicode_decimal": 59119
    },
    {
      "icon_id": "13745148",
      "name": "Right90_line",
      "font_class": "Right_line",
      "unicode": "e6b7",
      "unicode_decimal": 59063
    },
    {
      "icon_id": "10678401",
      "name": "back",
      "font_class": "back",
      "unicode": "e6db",
      "unicode_decimal": 59099
    },
    {
      "icon_id": "7766709",
      "name": "icon_add",
      "font_class": "icon_add",
      "unicode": "eb8f",
      "unicode_decimal": 60303
    },
    {
      "icon_id": "8776631",
      "name": "view",
      "font_class": "icon-test",
      "unicode": "e633",
      "unicode_decimal": 58931
    },
    {
      "icon_id": "8776676",
      "name": "view_off",
      "font_class": "icon-test1",
      "unicode": "e634",
      "unicode_decimal": 58932
    },
    {
      "icon_id": "657478",
      "name": "短信",
      "font_class": "duanxin",
      "unicode": "e647",
      "unicode_decimal": 58951
    },
    {
      "icon_id": "658017",
      "name": "个人",
      "font_class": "geren",
      "unicode": "e657",
      "unicode_decimal": 58967
    },
    {
      "icon_id": "658044",
      "name": "解锁",
      "font_class": "jiesuo",
      "unicode": "e669",
      "unicode_decimal": 58985
    },
    {
      "icon_id": "666883",
      "name": "人文",
      "font_class": "renwen",
      "unicode": "e68d",
      "unicode_decimal": 59021
    },
    {
      "icon_id": "666885",
      "name": "设置",
      "font_class": "shezhi",
      "unicode": "e68f",
      "unicode_decimal": 59023
    },
    {
      "icon_id": "666887",
      "name": "适中",
      "font_class": "shizhong",
      "unicode": "e691",
      "unicode_decimal": 59025
    },
    {
      "icon_id": "679755",
      "name": "简约的",
      "font_class": "jianyuede",
      "unicode": "e6df",
      "unicode_decimal": 59103
    },
    {
      "icon_id": "2674477",
      "name": "身份证",
      "font_class": "shenfenzheng",
      "unicode": "e625",
      "unicode_decimal": 58917
    }
  ]
}
